reckoner/__init__.py
reckoner/chart.py
reckoner/cli.py
reckoner/config.py
reckoner/course.py
reckoner/example-course.yml
reckoner/exception.py
reckoner/hooks.py
reckoner/importer.py
reckoner/kube.py
reckoner/manifests.py
reckoner/meta.py
reckoner/reckoner.py
reckoner/release.py
reckoner/repository.py
reckoner/assets/course.schema.json
reckoner/command_line_caller/__init__.py
reckoner/command_line_caller/tests/__init__.py
reckoner/command_line_caller/tests/test_command_line_caller.py
reckoner/helm/__init__.py
reckoner/helm/client.py
reckoner/helm/cmd_response.py
reckoner/helm/command.py
reckoner/helm/provider.py
reckoner/helm/tests/__init__.py
reckoner/helm/tests/test_client.py
reckoner/helm/tests/test_cmd_response.py
reckoner/helm/tests/test_provider.py
reckoner/schema_validator/__init__.py
reckoner/schema_validator/course.py
reckoner/secrets/__init__.py
reckoner/secrets/providers/__init__.py
reckoner/secrets/providers/aws_parameter_store.py
reckoner/secrets/providers/base.py
reckoner/secrets/providers/shell.py
reckoner/tests/__init__.py
reckoner/tests/namespace_manager_mock.py
reckoner/tests/test_chart.py
reckoner/tests/test_cli.py
reckoner/tests/test_config.py
reckoner/tests/test_course.py
reckoner/tests/test_hooks.py
reckoner/tests/test_importer.py
reckoner/tests/test_kube.py
reckoner/tests/test_manifests.py
reckoner/tests/test_meta.py
reckoner/tests/test_reckoner.py
reckoner/tests/test_repository.py
reckoner/tests/test_secrets.py
reckoner/tests/files/configmap.yaml
reckoner/tests/files/service.yaml
reckoner/tests/files/templates.yaml
reckoner/tests/files/templates2.yaml
reckoner/tests/files/templates3.yaml
reckoner/yaml/__init__.py
reckoner/yaml/handler.py
reckoner/yaml/tests/test_handler.py
reckoner-5.0.5.dist-info/LICENSE
reckoner-5.0.5.dist-info/METADATA
reckoner-5.0.5.dist-info/WHEEL
reckoner-5.0.5.dist-info/entry_points.txt
reckoner-5.0.5.dist-info/top_level.txt
reckoner-5.0.5.dist-info/RECORD
