Metadata-Version: 2.1
Name: reckoner
Version: 5.0.5
Summary: Declarative Helm configuration with Git capability
Home-page: https://fairwinds.com/
Author: FairwindsOps Inc.
Author-email: service@fairwinds.com
License: Apache2.0
Platform: UNKNOWN
Requires-Python: >=3.7
License-File: LICENSE
Requires-Dist: click (==8.0.1)
Requires-Dist: GitPython (>=2.1.11)
Requires-Dist: coloredlogs (>=9.0)
Requires-Dist: semver (>=2.8.1)
Requires-Dist: ruyaml (>=0.20.0)
Requires-Dist: jsonschema (>=3.0.2)
Requires-Dist: kubernetes (>=12.0.1)
Requires-Dist: boto3 (>=1.18.17)
